ajishCalc/__init__.py
ajishCalc/core.py
ajishcalc-0.1.0.dist-info/METADATA
ajishcalc-0.1.0.dist-info/WHEEL
ajishcalc-0.1.0.dist-info/top_level.txt
ajishcalc-0.1.0.dist-info/RECORD
