Metadata-Version: 2.4
Name: ajishCalc
Version: 0.1.0
Summary: Percentage calculator
Author-email: Ajish <you@example.com>
Requires-Python: >=3.7
